{
  "generatedAt": "2026-05-22T07:46:07.776Z",
  "briefing": {
    "mode": "for-you",
    "weekLabel": "May 16 – May 22",
    "headline": "Your week in markets and energy.",
    "summary": "From your lens as a investor tracking markets, the desk surfaced 8 stories that matter most to your briefing. Leading threads include: Walmart to report first-quarter earnings before the bell. Here's what Wall Street expects - CNBC; Elon Musk's SpaceX IPO filing is out - Axios. Prioritize what changes decisions you own; treat the rest as peripheral scan.",
    "keySignal": "Dominant theme · Markets leads the week; energy remains a secondary thread."
  }
}